scopuscaller/__init__.py
scopuscaller/call_scopus.py
scopuscaller/call_semanticscholar.py
scopuscaller/test_call_scopus.py
scopus_caller-0.1.4.dist-info/LICENSE
scopus_caller-0.1.4.dist-info/METADATA
scopus_caller-0.1.4.dist-info/WHEEL
scopus_caller-0.1.4.dist-info/top_level.txt
scopus_caller-0.1.4.dist-info/zip-safe
scopus_caller-0.1.4.dist-info/RECORD
