Metadata-Version: 2.1
Name: scopus-caller
Version: 0.1.4
Summary: This package allows the users to query its database for all the articles based on a specified keyword(s)
Home-page: https://github.com/vishalmhjn/scopus_caller
Author: Vishal Mahajan
Author-email: vishal.mahajan@tum.de
License: MIT
Keywords: example,setuptools
Classifier: License :: OSI Approved :: MIT License
Classifier: Programming Language :: Python :: 3
Requires-Python: >=3.8
License-File: LICENSE
Requires-Dist: aiohttp
Requires-Dist: nest-asyncio
Requires-Dist: numpy
Requires-Dist: pandas
Requires-Dist: requests
Requires-Dist: pytest
Requires-Dist: click
Requires-Dist: pylint
Requires-Dist: black
Requires-Dist: pytest-cov
